Metadata-Version: 1.2
Name: stackexplain
Version: 1.4.0
Summary: Command-line tool that automatically explains your error message using ChatGPT
Home-page: https://github.com/shobrook/stackexplain
Author: shobrook
Author-email: shobrookj@gmail.com
License: MIT
Keywords: chatgpt cli commandline error message stack trace stackexplain explanation
Platform: UNKNOWN
Classifier: Environment :: Console
Classifier: Intended Audience :: Developers
Classifier: Topic :: Software Development
Classifier: Topic :: Software Development :: Debuggers
Classifier: Natural Language :: English
Classifier: License :: OSI Approved :: MIT License
Classifier: Programming Language :: Python
Requires: revChatGPT
Requires: pygments
Requires-Python: >=3
